sharingiscaring/__init__.py
sharingiscaring/block.py
sharingiscaring/ccdscan.py
sharingiscaring/cis.py
sharingiscaring/cns.py
sharingiscaring/credential.py
sharingiscaring/enums.py
sharingiscaring/env.py
sharingiscaring/mongodb.py
sharingiscaring/node.py
sharingiscaring/pool.py
sharingiscaring/rewards.py
sharingiscaring/tooter.py
sharingiscaring/transaction.py
sharingiscaring/user_v2.py
sharingiscaring/GRPCClient/__init__.py
sharingiscaring/GRPCClient/health_pb2.py
sharingiscaring/GRPCClient/health_pb2.pyi
sharingiscaring/GRPCClient/health_pb2_grpc.py
sharingiscaring/GRPCClient/service_pb2.py
sharingiscaring/GRPCClient/service_pb2.pyi
sharingiscaring/GRPCClient/service_pb2_grpc.py
sharingiscaring/GRPCClient/types_pb2.py
sharingiscaring/GRPCClient/types_pb2.pyi
sharingiscaring/GRPCClient/types_pb2_grpc.py
sharingiscaring/GRPCClient/wadze.py
sharingiscaring/GRPCClient/CCD_Types/__init__.py
sharingiscaring/GRPCClient/concordium/__init__.py
sharingiscaring/GRPCClient/concordium/health/__init__.py
sharingiscaring/GRPCClient/concordium/v2/__init__.py
sharingiscaring/GRPCClient/queries/_CheckHealth.py
sharingiscaring/GRPCClient/queries/_GetAccountInfo.py
sharingiscaring/GRPCClient/queries/_GetAccountList.py
sharingiscaring/GRPCClient/queries/_GetAnonymityRevokers.py
sharingiscaring/GRPCClient/queries/_GetBakerEarliestWinTime.py
sharingiscaring/GRPCClient/queries/_GetBakerList.py
sharingiscaring/GRPCClient/queries/_GetBlockChainParameters.py
sharingiscaring/GRPCClient/queries/_GetBlockInfo.py
sharingiscaring/GRPCClient/queries/_GetBlockPendingUpdates.py
sharingiscaring/GRPCClient/queries/_GetBlockSpecialEvents.py
sharingiscaring/GRPCClient/queries/_GetBlockTransactionEvents.py
sharingiscaring/GRPCClient/queries/_GetBlocksAtHeight.py
sharingiscaring/GRPCClient/queries/_GetConsensusInfo.py
sharingiscaring/GRPCClient/queries/_GetElectionInfo.py
sharingiscaring/GRPCClient/queries/_GetFinalizedBlocks.py
sharingiscaring/GRPCClient/queries/_GetIdentityProviders.py
sharingiscaring-0.4.40.dist-info/METADATA
sharingiscaring-0.4.40.dist-info/WHEEL
sharingiscaring-0.4.40.dist-info/top_level.txt
sharingiscaring-0.4.40.dist-info/RECORD
