Metadata-Version: 2.1
Name: sharingiscaring
Version: 0.4.40
Summary: Shared code for Concordium Explorer (Bot)
Home-page: https://github.com/sderuiter/sharingiscaring
Author: Sander de Ruiter
Author-email: sdr@concordium-explorer.nl
License: MIT
Requires-Dist: rich
Requires-Dist: python-dateutil
Requires-Dist: base58
Requires-Dist: eth-hash
Requires-Dist: pycryptodome
Requires-Dist: pytest
Requires-Dist: leb128
Requires-Dist: pydantic
Requires-Dist: pymongo
Requires-Dist: motor
Requires-Dist: requests
Requires-Dist: apprise
Requires-Dist: py-graphql-client
Requires-Dist: chardet
